<?xml version="1.0" encoding="utf-8"?>
<PermissionSets>
  <PermissionSet RoleID="METEO SAMPLE ADDIN" RoleName="Meteo sample Addin">
    <Permission>
      <ObjectID>50130</ObjectID>
      <ObjectType>8</ObjectType>
      <ReadPermission>0</ReadPermission>
      <InsertPermission>0</InsertPermission>
      <ModifyPermission>0</ModifyPermission>
      <DeletePermission>0</DeletePermission>
      <ExecutePermission>1</ExecutePermission>
      <SecurityFilter />
    </Permission>
    <Permission>
      <ObjectID>50131</ObjectID>
      <ObjectType>8</ObjectType>
      <ReadPermission>0</ReadPermission>
      <InsertPermission>0</InsertPermission>
      <ModifyPermission>0</ModifyPermission>
      <DeletePermission>0</DeletePermission>
      <ExecutePermission>1</ExecutePermission>
      <SecurityFilter />
    </Permission>
    <Permission>
      <ObjectID>50132</ObjectID>
      <ObjectType>8</ObjectType>
      <ReadPermission>0</ReadPermission>
      <InsertPermission>0</InsertPermission>
      <ModifyPermission>0</ModifyPermission>
      <DeletePermission>0</DeletePermission>
      <ExecutePermission>1</ExecutePermission>
      <SecurityFilter />
    </Permission>
  </PermissionSet>
</PermissionSets>